cat/__init__.py
cat/main.py
cat/models.py
cat/agents/tabby/main.py
cat/agents/tabby/react.py
cat/agents/tabby/actions/__init__.py
cat/agents/tabby/actions/run_terminal_command.py
cat/agents/tabby/utils/ai.py
cat/utils/ai.py
ai_cat-0.0.2.dist-info/METADATA
ai_cat-0.0.2.dist-info/WHEEL
ai_cat-0.0.2.dist-info/entry_points.txt
ai_cat-0.0.2.dist-info/licenses/LICENSE
ai_cat-0.0.2.dist-info/RECORD
