Metadata-Version: 2.4
Name: ai-cat
Version: 0.0.2
Summary: Computer assisted tasks
Project-URL: Homepage, https://github.com/belindamo/cat
Project-URL: Issues, https://github.com/belindamo/cat/issues
Author-email: Belinda Mo <justanexperimentpark@gmail.com>
License-Expression: MIT
License-File: LICENSE
Requires-Python: >=3.11
Requires-Dist: dspy>=2.6.27
